README.rst
reqdump.py
setup.py
requests_dump.egg-info/PKG-INFO
requests_dump.egg-info/SOURCES.txt
requests_dump.egg-info/dependency_links.txt
requests_dump.egg-info/requires.txt
requests_dump.egg-info/top_level.txt