Metadata-Version: 1.1
Name: requests-dump
Version: 0.1.3
Summary: `requests-dump` provides hook functions for requests.
Home-page: https://github.com/torufurukawa/requests-dump
Author: Toru Furukawa
Author-email: torufurukawa@gmail.com
License: MIT
Keywords: http
Platform: UNKNOWN
Classifier: Development Status :: 1 - Planning
Classifier: License :: OSI Approved :: MIT License
Classifier: Programming Language :: Python
Classifier: Topic :: Software Development
